stegashade/__init__.py
stegashade/cli.py
stegashade/enc.py
stegashade/stega_shade.py
stegashade-0.3.dist-info/LICENSE
stegashade-0.3.dist-info/METADATA
stegashade-0.3.dist-info/WHEEL
stegashade-0.3.dist-info/entry_points.txt
stegashade-0.3.dist-info/top_level.txt
stegashade-0.3.dist-info/RECORD
