Metadata-Version: 2.1
Name: stegashade
Version: 0.3
Summary: Stega Shade CLI is a user-friendly command-line interface tool designed for image-based steganography. With a focus on simplicity and security, it provides functionality to encode and decode messages into images, including password-protected encoding for enhanced privacy. The tool is built using Python and leverages robust algorithms to ensure data integrity and secrecy.
Home-page: https://github.com/merwin-asm/StegaShade
Author: Merwin M
License: MIT
Platform: UNKNOWN
Classifier: Programming Language :: Python :: 3
Classifier: License :: OSI Approved :: MIT License
Classifier: Operating System :: OS Independent
License-File: LICENSE
Requires-Dist: Pillow
Requires-Dist: rich
Requires-Dist: numpy
Requires-Dist: cryptography
